fw_file_rs/__init__.py
fw_file_rs/fw_file_rs.abi3.so
fw_file_rs-0.5.2.dist-info/METADATA
fw_file_rs-0.5.2.dist-info/WHEEL
fw_file_rs-0.5.2.dist-info/RECORD
