Metadata-Version: 2.4
Name: fw-file-rs
Version: 0.5.2
Classifier: Programming Language :: Rust
Classifier: Programming Language :: Python :: Implementation :: CPython
Classifier: Programming Language :: Python :: Implementation :: PyPy
Summary: Read, parse and de-identify DICOM files
Home-Page: https://gitlab.com/flywheel-io/tools/lib/fw-file-rs
Author-email: Flywheel <support@flywheel.io>
License-Expression: MIT
Requires-Python: >=3.8
Project-URL: Documentation, https://gitlab.com/flywheel-io/tools/lib/fw-file-rs
Project-URL: Repository, https://gitlab.com/flywheel-io/tools/lib/fw-file-rs
